kedro_pytest/__init__.py
kedro_pytest/plugin.py
kedro_pytest/test_kedro.py
tests/__init__.py
tests/conftest.py
tests/test_test_kedro.py
kedro_pytest-0.1.3.dist-info/LICENSE
kedro_pytest-0.1.3.dist-info/METADATA
kedro_pytest-0.1.3.dist-info/WHEEL
kedro_pytest-0.1.3.dist-info/entry_points.txt
kedro_pytest-0.1.3.dist-info/top_level.txt
kedro_pytest-0.1.3.dist-info/RECORD
