Metadata-Version: 2.1
Name: kedro-pytest
Version: 0.1.3
Summary: Helps testing Kedro plugin.
Home-page: https://github.com/ProjetaAi/kedro_pytest
Author: nickolasrm
Author-email: nickolasrochamachado@gmail.com
License: MIT
Platform: any
License-File: LICENSE
Requires-Dist: kedro (>=0.18.2)
Requires-Dist: pytest
Requires-Dist: pytest-tmpfs
Requires-Dist: click
Requires-Dist: flatten-dict
Requires-Dist: PyYAML
Requires-Dist: pandas
Provides-Extra: dev
Requires-Dist: types-PyYAML ; extra == 'dev'
Requires-Dist: pytest-cov ; extra == 'dev'
Provides-Extra: test
Requires-Dist: pytest-cov ; extra == 'test'
